realcookie
