Metadata-Version: 1.1
Name: realcookie
Version: 1.0.9
Summary: Benolot's cookie API, python version
Home-page: https://github.com/secknv/cookie-api
Author: secknv
Author-email: UNKNOWN
License: MIT
Platform: UNKNOWN
Classifier: Development Status :: 5 - Production/Stable
Classifier: Intended Audience :: Developers
Classifier: Topic :: Software Development :: Libraries :: Python Modules
Classifier: License :: OSI Approved :: MIT License
Classifier: Programming Language :: Python :: 3.5
